[
    {
        "start_time": "0.00",
        "end_time": "10.01",
        "captions": [
            "a man sitting in a chair with his arm up and another person standing behind him",
            "a man sitting in a chair with his hand on the lap, and another standing behind him",
            "an old man with a cigarette in his mouth, and another person standing behind him",
            "a man smoking a cigarette in the dark room of a house, and a woman in the background",
            "an old man with a cigarette in his mouth, sitting on a chair in the background is a woman standing"
        ]
    },
    {
        "start_time": "10.01",
        "end_time": "15.39",
        "captions": [
            "a man in a room looking out a window with his hand on the wall,",
            "a man standing in front of a window looking out at the view of a city",
            "a person looking out a window at something in the room that is in front of them",
            "a person standing in front of a window with the sky behind him and his hand on the wall",
            "a man standing in front of a window with a bird on it's shoulder"
        ]
    },
    {
        "start_time": "15.39",
        "end_time": "54.85",
        "captions": [
            "a man standing on top of a building in the dark with his hands out to him",
            "a man standing in the dark with a ladder behind him and looking into the camera",
            "a person standing in the dark, with a camera in their hand, looking out of a window",
            "two people standing in the dark with one person holding an object and another standing next to them",
            "two people standing next to each other person on a ladder in the dark room with a ladder"
        ]
    },
    {
        "start_time": "54.85",
        "end_time": "74.99",
        "captions": [
            "a person in bed with the window open and a mirror on it, next to a tv",
            "a person in a room with a cribt and a baby in the cribt",
            "a woman in a cribt room with a baby next to her, a man standing in the background",
            "two people in a room with furniture and a bed in the background is a woman standing on",
            "a man looking at a woman in the mirror, with a man standing behind him"
        ]
    },
    {
        "start_time": "74.99",
        "end_time": "78.24",
        "captions": [
            "a white flower on a black background, with the words ` ` `'in white letters",
            "the moon in the sky with a few clouds above it, and an earth planet in the moon is in the background",
            "the moon in the sky with the moon behind it and a full moon in the background",
            "the moon in the night sky with the moon behind it and an orange sky in the background",
            "the moon with a red and blue sky in the background of the night sky, with the"
        ]
    }
]