[
    {
        "start_time": 0.0,
        "end_time": 8.88,
        "motion": 1.1711474722030604
    },
    {
        "start_time": 8.88,
        "end_time": 12.26,
        "motion": 0.6901913471519947
    },
    {
        "start_time": 12.26,
        "end_time": 33.32,
        "motion": 2.1516098934743138
    },
    {
        "start_time": 33.32,
        "end_time": 59.77,
        "motion": 1.5473583331654783
    },
    {
        "start_time": 59.77,
        "end_time": 97.72,
        "motion": 0.5271260957295149
    }
]